_gamsxcc.cp38-win32.pyd
gamsxcc/__init__.py
gamsxcc/gamsxcc.i
gamsxcc/gamsxcc.py
gamsxcc/C/gamsxcc.c
gamsxcc/C/gamsxcc.h
gamsxcc/C/gamsxcc_wrap.c
gamsxcc/C/gclgms.c
gamsxcc/C/gclgms.h
gamsxcc-1.post2492.dist-info/LICENSE
gamsxcc-1.post2492.dist-info/METADATA
gamsxcc-1.post2492.dist-info/WHEEL
gamsxcc-1.post2492.dist-info/top_level.txt
gamsxcc-1.post2492.dist-info/RECORD
