Metadata-Version: 2.1
Name: gamsxcc
Version: 1.post2492
Summary: Python library to access GAMS Execution Object
Home-page: UNKNOWN
Author: GAMS Development Corp.
Maintainer: kavvkon
Maintainer-email: kavvkon@gmail.com
License: THE GAMS FREE APIS ARE PROVIDED "AS IS" AND GAMS DISCLAIMS ALL WARRANTIES WITH REGARD TO THIS SOFTWARE INCLUDING ALL IMPLIED WARRANTIES OF MERCHANTABILITY AND FITNESS. IN NO EVENT SHALL GAMS BE LIABLE FOR ANY SPECIAL, DIRECT, INDIRECT, OR CONSEQUENTIAL DAMAGES OR ANY DAMAGES WHATSOEVER RESULTING FROM LOSS OF USE, DATA OR PROFITS, WHETHER IN AN ACTION OF CONTRACT, NEGLIGENCE OR OTHER TORTIOUS ACTION, ARISING OUT OF OR IN CONNECTION WITH THE USE OR PERFORMANCE OF THE GAMS FREE APIS.
Platform: UNKNOWN
